Metadata-Version: 2.1
Name: sportinf
Version: 1.1.2
Summary: Package to get sport information
Home-page: https://github.com/AlexBlackHawk/sportinf
Author: alexm
Author-email: alex.maudza@gmail.com
License: MIT
Download-URL: https://github.com/AlexBlackHawk/sportinf/archive/refs/tags/1.1.2.tar.gz
Keywords: sportinf,sport,scores,statistic
Platform: UNKNOWN
Requires-Python: >=3
License-File: LICENSE.txt
